thunagen/__init__.py
thunagen/common.py
thunagen/conf.py
thunagen/functions.py
thunagen-0.3.8.dist-info/WHEEL
thunagen-0.3.8.dist-info/METADATA
thunagen-0.3.8.dist-info/RECORD
