Metadata-Version: 2.1
Name: thunagen
Version: 0.3.8
Summary: Google Cloud function to generate thumbnail for images in Google Storage.
Home-page: https://github.com/sunshine-tech/thunagen.git
License: Apache-2.0
Keywords: google,cloud,storage,functions,thumbnail
Author: Nguyễn Hồng Quân
Author-email: ng.hong.quan@gmail.com
Maintainer: Nguyễn Hồng Quân
Maintainer-email: ng.hong.quan@gmail.com
Requires-Python: >=3.7,<4.0
Classifier: Environment :: Web Environment
Classifier: Intended Audience :: Developers
Classifier: Intended Audience :: System Administrators
Classifier: License :: OSI Approved :: Apache Software License
Classifier: Programming Language :: Python :: 3
Classifier: Programming Language :: Python :: 3.7
Classifier: Programming Language :: Python :: 3.8
Classifier: Topic :: Multimedia :: Graphics :: Graphics Conversion
Requires-Dist: Pillow (>=7.0.0,<8.0.0)
Requires-Dist: google-cloud-pubsub (>=1.1.0,<2.0.0)
Requires-Dist: google-cloud-storage (>=1.24.1,<2.0.0)
Requires-Dist: importlib_metadata (>=1.3.0,<2.0.0)
Requires-Dist: lazy_object_proxy (>=1.4.3,<2.0.0)
Requires-Dist: logbook (>=1.5.3,<2.0.0)
Requires-Dist: pendulum (>=2.0.5,<3.0.0)
Requires-Dist: python-dotenv (>=0.10.3,<0.11.0)
Requires-Dist: single-version (>=1.1,<2.0)
Project-URL: Repository, https://github.com/sunshine-tech/thunagen.git
